{
    "featureData": [
        {
            "id": 37,
            "position": [
                0.024772059555658643,
                0.0047952714350449465
            ],
            "pivotOffset": [
                0,
                0,
                0
            ],
            "mbb": [
                -13.225386250380865,
                -13.245363038501479,
                -7.3874186584725976,
                13.274930369492182,
                13.254953581371568,
                19.112897961400449
            ],
            "layer": "Building",
            "geometries": [
                {
                    "id": 37,
                    "type": "GeometryReference",
                    "params": {
                        "$ref": "/geometryData/1",
                        "faceRange": [
                            0,
                            373
                        ]
                    }
                }
            ]
        }
    ],
    "geometryData": [
        {
            "id": 1,
            "type": "ArrayBufferView",
            "transformation": [
                1.0,
                0.0,
                0.0,
                0.0,
                0.0,
                1.0,
                0.0,
                0.0,
                0.0,
                0.0,
                1.0,
                0.0,
                0.0,
                0.0,
                0.0,
                1.0
            ],
            "params": {
                "type": "triangles",
                "material": "/materialDefinitions/Mat574",
                "texture": "/textureDefinitions/574",
                "vertexAttributes": {
                    "position": {
                        "byteOffset": 8,
                        "count": 1122,
                        "valueType": "Float32",
                        "valuesPerElement": 3
                    },
                    "normal": {
                        "byteOffset": 13472,
                        "count": 1122,
                        "valueType": "Float32",
                        "valuesPerElement": 3
                    },
                    "uv0": {
                        "byteOffset": 26936,
                        "count": 1122,
                        "valueType": "Float32",
                        "valuesPerElement": 2
                    },
                    "color": {
                        "byteOffset": 35912,
                        "count": 1122,
                        "valueType": "UInt8",
                        "valuesPerElement": 4
                    },
                    "region": {
                        "byteOffset": 40400,
                        "count": 1122,
                        "valueType": "UInt16",
                        "valuesPerElement": 4
                    }
                },
                "featureAttributes": {
                    "id": {
                        "byteOffset": 49376,
                        "count": 1,
                        "valueType": "UInt64",
                        "valuesPerElement": 1
                    },
                    "faceRange": {
                        "byteOffset": 49384,
                        "count": 1,
                        "valueType": "UInt32",
                        "valuesPerElement": 2
                    }
                }
            }
        }
    ]
}