{
    "min": 1.0,
    "max": 12.0,
    "avg": 5.63104,
    "stddev": 2.629335,
    "count": 3799022.0,
    "sum": 21392446.0,
    "variance": 6.913403,
    "histogram": {
        "minimum": 1.0,
        "maximum": 12.0,
        "counts": [
            14,
            802764,
            681975,
            3056,
            153,
            387412,
            4948,
            1904257,
            9987,
            4073,
            383
        ]
    },
    "mostFrequentValues": [
        {
            "value": 8.0,
            "count": 1904257
        },
        {
            "value": 2.0,
            "count": 802764
        },
        {
            "value": 3.0,
            "count": 681975
        },
        {
            "value": 6.0,
            "count": 387412
        },
        {
            "value": 9.0,
            "count": 9987
        },
        {
            "value": 7.0,
            "count": 4948
        },
        {
            "value": 10.0,
            "count": 4073
        },
        {
            "value": 4.0,
            "count": 3056
        },
        {
            "value": 11.0,
            "count": 383
        },
        {
            "value": 5.0,
            "count": 153
        },
        {
            "value": 1.0,
            "count": 14
        }
    ]
}